SLAVE/AHB_SLAVE.v
module AHB_SLAVE #(parameter DATA_WIDTH = 16,ADDR_WIDTH = 16)(

    //GENERAL SIGNALS
    input wire HCLK,
    input wire RESET,                       // Active LOW
    //AMBA AHB SIGNALS
 
    //Signals from MASTER
    input wire [ADDR_WIDTH-1:0] HADDR,      // ADDR to slave, lasts for a single HCLK cycle
    input wire [DATA_WIDTH-1:0] HWDATA,     // DATA form Master to Slave
    input wire [2:0] HBURST,                // BURST type : single incr wrap
    input wire [2:0] HSIZE,                 // SIZE of transfer : byte, halfword or word - max 1024bits
    input wire [1:0] HTRANS,                // Transfer type:  IDLE,BUSY,NONSEQ,SEQ
    input wire HWRITE,                      // Transfer direction: HIGH-write, LOW-read
    input wire HMASTLOCK ,                   // HIGH when locked sequence

       //Signals from SLAVE
    output reg [DATA_WIDTH-1:0] HRDATA,     // DATA form Slave to master
    output reg HREADY,                      // When HIGH-transfer finished, LOW to extend transfer
    output wire HRESP                       // Transfer status(HERE ALWAYS OKAY) : LOW- OKAY, HIGH-ERROR

    
);
    //DLEN types
    localparam [1:0] SingleData = 2'b00;
    localparam [1:0] OneRow     = 2'b01;
    localparam [1:0] Brst2Row   = 2'b10;

    //HTRANS TYPES
    localparam [1:0] IDLE       = 2'b00;
    localparam [1:0] BUSY       = 2'b01;    //Not used
    localparam [1:0] NONSEQ     = 2'b10;
    localparam [1:0] SEQ        = 2'b11;

    //HBURST TYPES
    localparam [2:0] SINGLE     = 3'b000;
    localparam [2:0] INCR       = 3'b001;

    //AHB SIZES
    localparam [2:0] HALFWORD   = 3'b001;   // 16bits   USED


    //Unused signals
    assign  HRESP               = 1'b0;
   // assign  HREADY              = 1'b1;

    //Local REGs
    reg [3:0]             STATE;  //  //

    reg [DATA_WIDTH-1:0]  RAM [0:65535];
   
    reg [15:0]            adres;
    wire[DATA_WIDTH-1:0] ram1;
    wire[DATA_WIDTH-1:0] ram2;
    wire[DATA_WIDTH-1:0] ram3;
    wire[DATA_WIDTH-1:0] ram4;
    wire[DATA_WIDTH-1:0] ram5;
    assign ram1  = RAM[10] ;
    assign ram2  = RAM[11] ;
    assign ram3  = RAM[12] ;
    assign ram4  = RAM[13] ;
    assign ram5  = RAM[20] ;
    reg [3:0] iterator;



    //States
    localparam [3:0] IDLE_STATE             = 4'b0000;
    localparam [3:0] SINGLE_WRITE           = 4'b0001;
    localparam [3:0] SINGLE_READ            = 4'b0010;

    localparam [3:0] BURST_READ             = 4'b1100;
    localparam [3:0] BURST_WRITE            = 4'b0011;

always @(*) begin
  adres = HADDR;
end



always @(posedge HCLK or negedge RESET ) begin
    if (RESET == 1'b0) begin
        HRDATA  <= {DATA_WIDTH{1'b0}};
        STATE   <=  IDLE_STATE;
        HREADY <= 1'b1;
        RAM [0] = 0;
        RAM [1] = 20;
        RAM [2] = 30;
        RAM [3] = 40;
        RAM [4] = 50;
        RAM [5] = 60;
        RAM [6] = 70;
        RAM [7] = 80;
        RAM [8] = 90;
        RAM [9] = 100;
        RAM [10] = 110;
        RAM [11] = 120;
        RAM [12] = 130;
        RAM [13] = 140;
        RAM [14] = 150;
        RAM [15] = 160;
        RAM [16] = 170;
        RAM [17] = 180;
        RAM [18] = 190;
        RAM [19] = 200;

    end
    else begin
        case(STATE)
    IDLE_STATE: begin
    if(HTRANS != IDLE ) begin
        if(HWRITE == 1'b1) begin
            if(HBURST == SINGLE) begin
                STATE <= SINGLE_WRITE;
            end else begin
                STATE <= BURST_WRITE;
            end
        end else begin
            if(HBURST == SINGLE) begin
                STATE <= SINGLE_READ;
            end else begin
                STATE <= BURST_READ;
               HRDATA = RAM[adres];
            end
        end
     end else begin
         STATE<= IDLE_STATE;
         HRDATA <= 16'd0;
         iterator = 0;
     end
     end

    SINGLE_WRITE: begin
        RAM[HADDR] <= HWDATA;   //dziala
        STATE <= IDLE_STATE;
     end
    SINGLE_READ: begin
        HRDATA <= RAM[adres];
        STATE <= IDLE_STATE;
     end
    BURST_READ: begin
        HRDATA = RAM[adres];
        iterator = iterator+1;
        if(HTRANS != IDLE && iterator < 3) begin
            STATE<= BURST_READ;
        end else begin
            STATE<= IDLE_STATE;
        end
    end
    BURST_WRITE: begin              //DZIALA
        if(HTRANS != IDLE) begin
            STATE<= BURST_WRITE;
            RAM[adres]<= HWDATA;
        end else begin
            STATE<= IDLE_STATE;

        end
    end





endcase
  end
    
end


endmodule

SLAVE/AHB_MASTER1.v
`include "AHB_SLAVE.v"
module AHB_MASTER #(parameter DATA_WIDTH = 16,ADDR_WIDTH = 16)(

    //GENERAL SIGNALS
    input wire HCLK,
    input wire RESET,                       // Active LOW
    //AMBA AHB SIGNALS
    //Signals from SLAVE
  
    //CONF REGISTERs INPUTs
    input wire                   REGs_ready,// 1 when regs are available
    input wire [ADDR_WIDTH-1:0]  DADR,      //goes to HADDR, addres of data
    input wire [ADDR_WIDTH-1:0]  CADR,      //goes to HADDR, where save the sum
    input wire [1:0]             DLEN,    //Singl edata 16bit 00|one row 16bit x4 01| 10 Burst 2 rows 16bit x4 x2
    input wire                   isSumReady,
    input wire [DATA_WIDTH-1:0]  SUM1,
    input wire [DATA_WIDTH-1:0]  SUM2,
    input wire [DATA_WIDTH-1:0]  SUM3,
    input wire [DATA_WIDTH-1:0]  SUM4,
    input wire [DATA_WIDTH-1:0]  SUM5,
    input wire [DATA_WIDTH-1:0]  SUM6,
    input wire [DATA_WIDTH-1:0]  SUM7,
    input wire [DATA_WIDTH-1:0]  SUM8,
  //  input wire [DATA_WIDTH-1:0]  DATA_AHB_IN,
 //   input wire                   fifo_out_empty,
  //  input wire                   fifo_in_full,
  //  output reg                   rd_en_fifo_out,
    output reg [DATA_WIDTH-1:0]  DATA_AHB_OUT
 //   output reg                   wr_en_fifo_in
    //MASTER OUT

    
);
    //DLEN types
    localparam [1:0] SingleData = 2'b00;
    localparam [1:0] OneRow     = 2'b01;
    localparam [1:0] Brst2Row   = 2'b10;

    //HTRANS TYPES
    localparam [1:0] IDLE       = 2'b00;
    localparam [1:0] BUSY       = 2'b01;    //Not used
    localparam [1:0] NONSEQ     = 2'b10;
    localparam [1:0] SEQ        = 2'b11;

    //HBURST TYPES
    localparam [2:0] SINGLE     = 3'b000;
    localparam [2:0] INCR       = 3'b001;

    // NOT USED 
    localparam [2:0] WRAP4      = 3'b010;  
    localparam [2:0] INCR4      = 3'b011;   
    localparam [2:0] WRAP8      = 3'b100;   
    localparam [2:0] INCR8      = 3'b101;   
    localparam [2:0] WRAP16     = 3'b110;   
    localparam [2:0] INCR16     = 3'b111;
    //

    //AHB SIZES
    localparam [2:0] BYTE       = 3'b000;   // 8bits    NOTused
    localparam [2:0] HALFWORD   = 3'b001;   // 16bits   USED
    localparam [2:0] WORD       = 3'b010;   // 32bits   NOTused

    //Unused signals


    //Local REGs
    reg [3:0]             STATE;  //  //

    reg [ADDR_WIDTH-1:0]  rDADR;      //goes to HADDR, addres of data
    reg [ADDR_WIDTH-1:0]  rCADR;      //goes to HADDR, where save the sum
    reg [1:0]             rDLEN; 
    reg [DATA_WIDTH-1:0]  DataFromSlave[0:7];
    reg                   WhichBurst; // 0- oneRow, 1-doubleRow
    reg                   isFinished;
    reg [2:0]             iterator;
    reg [DATA_WIDTH-1:0] SUM [0:7];





     wire [DATA_WIDTH-1:0] HRDATA;     // DATA form Slave to master
     wire HREADY;                    // When HIGH-transfer finished, LOW to extend transfer
     wire HRESP;                       // Transfer status(HERE ALWAYS OKAY) : LOW- OKAY, HIGH-ERROR

     reg [ADDR_WIDTH-1:0] HADDR;      // ADDR to slave, lasts for a single HCLK cycle
    reg [DATA_WIDTH-1:0] HWDATA;     // DATA form Master to Slave
     reg [2:0] HBURST;                // BURST type : single incr wrap
     wire [2:0] HSIZE;                 // SIZE of transfer : byte, halfword or word - max 1024bits
     reg [1:0] HTRANS;              // Transfer type:  IDLE,BUSY,NONSEQ,SEQ
     reg HWRITE;                      // Transfer direction: HIGH-write, LOW-read
     wire HMASTLOCK;                    // HIGH when locked sequence
    assign HMASTLOCK            = 1'b0  ;
    assign HSIZE                = 3'b001;

    //States
    localparam [3:0] IDLE_STATE             = 4'b0000;
    localparam [3:0] SINGLE_ADDRES          = 4'b0001;
    localparam [3:0] SINGLE_DATA_READ       = 4'b0010;
    localparam [3:0] SINGLE_DATA_WRITE      = 4'b0100;
    localparam [3:0] SINGLE_STOP            = 4'b1000;
    localparam [3:0] BURST_START            = 4'b1110;
    localparam [3:0] BURST_RD_NEXT          = 4'b1100;
    localparam [3:0] BURST_WR_NEXT          = 4'b0011;
    localparam [3:0] BURST_STOP             = 4'b1010;

always @(*) begin
    SUM[0] = SUM1;
    SUM[1] = SUM2;
    SUM[2] = SUM3;
    SUM[3] = SUM4;
    SUM[4] = SUM5;
    SUM[5] = SUM6;
    SUM[6] = SUM7;
    SUM[7] = SUM8;
end


always @(posedge HCLK or negedge RESET ) begin
    if (RESET == 1'b0) begin
        HADDR   <= {ADDR_WIDTH{1'b0}};
        HWDATA  <= {DATA_WIDTH{1'b0}};
        HBURST  <=  SINGLE;
        HWRITE  <=  1'b0;
        STATE   <=  IDLE_STATE;
        HTRANS  <=  IDLE; 
    end
    else begin
        case(STATE)
    IDLE_STATE: begin
    HADDR = 16'd0;
  
        if(HREADY == 1'b1) begin
            if(isFinished == 0) begin
                if(HBURST == SINGLE)begin 
                    STATE  <= SINGLE_ADDRES;
                    HTRANS <= NONSEQ;
                end
                else begin  
                    STATE  <= BURST_START; 
                    iterator <= 0; 
                    HTRANS <= IDLE; 
                end
            end else begin
                STATE  <= IDLE_STATE;
                HTRANS <= IDLE;
                HWDATA <= 16'd0;
            end
        end
        else begin
            STATE  <= IDLE_STATE;
            HTRANS <= IDLE;
            HWDATA <= 16'd0;
        end
    end

    SINGLE_ADDRES: begin
        if(HREADY == 1'b1) begin
            if(HWRITE == 1'b1) begin
            STATE  <= SINGLE_DATA_WRITE;
            HTRANS <= NONSEQ;
            HADDR <= rCADR;
        end
        else begin
            STATE  <= SINGLE_DATA_READ;
            HTRANS <= NONSEQ;
            HADDR   <= rDADR;
        end
    end
    end

    SINGLE_DATA_READ: begin
        if(HREADY==1'b1) begin
            DataFromSlave[0] = HRDATA;
            isFinished <= 1;
            STATE <= SINGLE_STOP;
            HTRANS <= IDLE;

        end
        else begin
            STATE <= SINGLE_DATA_READ;
            HTRANS <= NONSEQ;
        end
    end

    SINGLE_DATA_WRITE: begin
        if(HREADY == 1'b1) begin
            HWDATA = SUM[0];
            isFinished <= 1;
            STATE <= SINGLE_STOP;
            HTRANS <= IDLE;
            HADDR <= 16'd0;

        end else begin
            HWDATA <= SUM[0];
            STATE <= SINGLE_DATA_WRITE;
            HTRANS <= NONSEQ;
        end
    end

    SINGLE_STOP: begin
        STATE <= IDLE_STATE;
        HTRANS <= IDLE;
        HWDATA <= 16'd0;
        HADDR <= 16'd0;

    end


    BURST_START: begin
        if(HREADY == 1'b1) begin
            if(HWRITE == 1'b1) begin
                HTRANS <= NONSEQ;
                STATE <= BURST_WR_NEXT;
                HADDR <= rCADR; 
                
            end else begin
                HTRANS <= NONSEQ;
                STATE <= BURST_RD_NEXT;
                HADDR <= rDADR;
            end 
       end    
       else begin
            STATE <= BURST_START;
            HTRANS <= NONSEQ;
        end

    end
    BURST_RD_NEXT: begin
        if(HREADY == 1'b1) begin
     //       if(!fifo_in_full) begin
            if(WhichBurst == 1'b0) begin
                if(iterator < 3) begin
                    STATE <= BURST_RD_NEXT;
                    HTRANS <= SEQ;
                    HADDR = HADDR + 1;
                    DataFromSlave[iterator] <= HRDATA;
                   DATA_AHB_OUT= HRDATA;
              //      wr_en_fifo_in = 1'b1;
                    iterator = iterator + 1;
                end else begin
                    STATE <= BURST_STOP;
                    DataFromSlave[iterator] <= HWDATA;
                    DATA_AHB_OUT = HRDATA;
             //       wr_en_fifo_in = 1'b1;
                    HADDR <= 16'd0;
                end
            end else begin
                if(iterator < 7) begin
                    STATE <= BURST_RD_NEXT;
                    HTRANS <= SEQ;
                    HADDR = HADDR + 1;
                    DataFromSlave[iterator] <= HRDATA;
                    DATA_AHB_OUT = HRDATA;
              //      wr_en_fifo_in = 1'b1;
                    iterator = iterator+1;
                end else begin
                    STATE <= BURST_STOP;
                    DataFromSlave[iterator] <= HWDATA;
                    DATA_AHB_OUT = HRDATA;
              //      wr_en_fifo_in = 1'b1;
                    HADDR <= 16'd0;                    
                end
           // end
            end
        end else begin
            STATE <= BURST_RD_NEXT;
        end
    end

        BURST_WR_NEXT: begin
        if(HREADY == 1'b1) begin
  //      if(!fifo_out_empty) begin
            if(WhichBurst == 1'b0) begin
                if(iterator < 3) begin
                    STATE <= BURST_WR_NEXT;
                    HTRANS <= SEQ;
                    HADDR = HADDR + 1;
                     HWDATA <= SUM[iterator];
              //      HWDATA <= DATA_AHB_IN;
               //     rd_en_fifo_out <= 1;
                    iterator = iterator + 1;
                end else begin
                    STATE <= BURST_STOP;
                    HWDATA <= SUM[iterator];//DATA_AHB_IN;
                 //   rd_en_fifo_out <= 1;
                    HADDR <= 16'd0;
                end
            end else begin
                if(iterator < 7) begin
                    STATE <= BURST_WR_NEXT;
                    HTRANS <= SEQ;
                    HADDR = HADDR + 1;
                     HWDATA <= SUM[iterator];
                   // rd_en_fifo_out <= 1;
                    iterator = iterator + 1;
                end else begin
                    STATE <= BURST_STOP;
                     HWDATA <= SUM[iterator];
                   // rd_en_fifo_out <= 1;
                    HADDR <= 16'd0;

                end
         //   end
            end
        end else begin
            STATE <= BURST_WR_NEXT;
        end
    end


    BURST_STOP: begin
        STATE <= IDLE_STATE;
        HTRANS <= IDLE;
        DATA_AHB_OUT = HRDATA;
        isFinished = 1'b1;
        iterator <= 0;
        HWDATA <= 16'd0;
        HADDR <= 16'd0;
      //  rd_en_fifo_out = 0;
     //   wr_en_fifo_in = 0;
        end


    endcase

    end
end

always @(posedge REGs_ready) begin
    rDLEN = DLEN;      
    rCADR = CADR;
    rDADR = DADR;
    isFinished = 1'b0;
end

always @(*) begin
    if(isSumReady == 1'b0) begin
        HWRITE = 1;  
    end else begin
        HWRITE = 0;
    end
end

always @(*) begin
    case(rDLEN)
    SingleData: begin
        HBURST = SINGLE;
        end

    OneRow: begin
        HBURST = INCR;
        WhichBurst = 1'b0;
    end

    Brst2Row: begin
        HBURST = INCR;
        WhichBurst = 1'b1;
    end
    endcase
    
end

AHB_SLAVE u1 (
    .HCLK(HCLK),
    .RESET(RESET),
    .HADDR(HADDR),
    .HWDATA(HWDATA),
    .HBURST(HBURST),
    .HSIZE(HSIZE),
    .HTRANS(HTRANS),
    .HWRITE(HWRITE),
    .HMASTLOCK(HMASTLOCK),
    .HRDATA(HRDATA),
    .HREADY(HREADY),
    .HRESP(HRESP)
    );

endmodule

SLAVE/AHB_MASTER_tb.v
module AHB_MASTER_tb ;

	//INPUTs REGs
	 reg 							HCLK;
	 reg 							RESET;
	 reg				[16-1:0]	HRDATA;
	 reg							HREADY;
	 reg							HRESP;
	 reg							REGs_ready;
	 reg 				[16-1:0]	DADR;	
	 reg 				[16-1:0]	CADR;
	 reg 				[1:0]		DLEN;
	 reg 							isSumReady;
	 reg 				[16-1:0]	SUM1;
	 reg 				[16-1:0]	SUM2;
	 reg 				[16-1:0]	SUM3;
	 reg 				[16-1:0]	SUM4;
	 reg 				[16-1:0]	SUM5;
	 reg 				[16-1:0]	SUM6;
	 reg 				[16-1:0]	SUM7;
	 reg 				[16-1:0]	SUM8;




	//OUTPUTs



	 AHB_MASTER #(.DATA_WIDTH(16), .ADDR_WIDTH(16) ) U0 (
	 	.HCLK 			(HCLK),
	 	.RESET 			(RESET),
	 	.REGs_ready 	(REGs_ready),
	 	.DADR 			(DADR),
	 	.CADR 			(CADR),
	 	.DLEN 			(DLEN),
	 	.isSumReady		(isSumReady),
	 	.SUM1 			(SUM1),
	 	.SUM2 			(SUM2),
	 	.SUM3 			(SUM3),
	 	.SUM4 			(SUM4),
	 	.SUM5 			(SUM5),
	 	.SUM6 			(SUM6),
	 	.SUM7 			(SUM7),
	 	.SUM8 			(SUM8)
	 	);







	 initial begin
	 #1 HCLK = 0;
	 #2 RESET = 1 ;
	 #2 RESET = 0 ;
	  	#10 RESET = 1;
 

	 #3 REGs_ready = 0;
	 isSumReady = 0;
	  	SUM1 = 12;
	 	SUM2= 3;
	 	SUM3 = 4;
	 	SUM4 = 2;
	 	SUM5 = 8;
	 	SUM6 = 1;
	 	SUM7 =3;
	 	SUM8 = 10;
	 #2	isSumReady = 1;
	 #2 DADR = 16'd1;
	 	DLEN = 2'b00;
	 	CADR = 16'd20;
	 #2 REGs_ready = 1;

	 #5REGs_ready = 0;
	 isSumReady = 0;
	 




	 #30
	  	SUM1 = 15;
	 	SUM2= 9;
	 	SUM3 = 89;
	 	SUM4 = 78;
	 	SUM5 = 67;
	 	SUM6 = 56;
	 	SUM7 =45;
	 	SUM8 = 34;
	 #2	isSumReady = 1;
	 #2 DADR = 16'd1;
	 	DLEN = 2'b01;
	 	CADR = 16'd10;
	 #1 REGs_ready = 1;
	 #2 REGs_ready = 0;	

	#30
	#2	isSumReady = 0;
	#2 	DADR = 16'd10;
	 	DLEN = 2'b01;
	 	CADR = 16'd10;
	 	#2 REGs_ready = 1;



		end

	always  
	
	#1 HCLK = !HCLK;



	initial begin
		$dumpfile ("AHB_MAST.vcd");
		$dumpvars;
	end
	

	initial begin
		
 	#300 $finish;
 	end





endmodule

SLAVE/AHB_MAST.vcd
$date
	Mon Jun 19 08:32:39 2017
$end
$version
	Icarus Verilog
$end
$timescale
	1s
$end
$scope module AHB_MASTER_tb $end
$var reg 16 ! CADR [15:0] $end
$var reg 16 " DADR [15:0] $end
$var reg 2 # DLEN [1:0] $end
$var reg 1 $ HCLK $end
$var reg 1 % REGs_ready $end
$var reg 1 & RESET $end
$var reg 16 ' SUM1 [15:0] $end
$var reg 16 ( SUM2 [15:0] $end
$var reg 16 ) SUM3 [15:0] $end
$var reg 16 * SUM4 [15:0] $end
$var reg 16 + SUM5 [15:0] $end
$var reg 16 , SUM6 [15:0] $end
$var reg 16 - SUM7 [15:0] $end
$var reg 16 . SUM8 [15:0] $end
$var reg 1 / isSumReady $end
$scope module U0 $end
$var wire 16 0 CADR [15:0] $end
$var wire 16 1 DADR [15:0] $end
$var wire 2 2 DLEN [1:0] $end
$var wire 1 $ HCLK $end
$var wire 1 3 HMASTLOCK $end
$var wire 1 4 HRESP $end
$var wire 3 5 HSIZE [2:0] $end
$var wire 1 % REGs_ready $end
$var wire 1 & RESET $end
$var wire 16 6 SUM1 [15:0] $end
$var wire 16 7 SUM2 [15:0] $end
$var wire 16 8 SUM3 [15:0] $end
$var wire 16 9 SUM4 [15:0] $end
$var wire 16 : SUM5 [15:0] $end
$var wire 16 ; SUM6 [15:0] $end
$var wire 16 < SUM7 [15:0] $end
$var wire 16 = SUM8 [15:0] $end
$var wire 1 / isSumReady $end
$var wire 1 > HREADY $end
$var wire 16 ? HRDATA [15:0] $end
$var reg 16 @ DATA_AHB_OUT [15:0] $end
$var reg 16 A HADDR [15:0] $end
$var reg 3 B HBURST [2:0] $end
$var reg 2 C HTRANS [1:0] $end
$var reg 16 D HWDATA [15:0] $end
$var reg 1 E HWRITE $end
$var reg 4 F STATE [3:0] $end
$var reg 1 G WhichBurst $end
$var reg 1 H isFinished $end
$var reg 3 I iterator [2:0] $end
$var reg 16 J rCADR [15:0] $end
$var reg 16 K rDADR [15:0] $end
$var reg 2 L rDLEN [1:0] $end
$scope module u1 $end
$var wire 16 M HADDR [15:0] $end
$var wire 3 N HBURST [2:0] $end
$var wire 1 $ HCLK $end
$var wire 1 3 HMASTLOCK $end
$var wire 1 4 HRESP $end
$var wire 3 O HSIZE [2:0] $end
$var wire 2 P HTRANS [1:0] $end
$var wire 16 Q HWDATA [15:0] $end
$var wire 1 E HWRITE $end
$var wire 1 & RESET $end
$var wire 16 R ram1 [15:0] $end
$var wire 16 S ram2 [15:0] $end
$var wire 16 T ram3 [15:0] $end
$var wire 16 U ram4 [15:0] $end
$var wire 16 V ram5 [15:0] $end
$var reg 16 W HRDATA [15:0] $end
$var reg 1 > HREADY $end
$var reg 4 X STATE [3:0] $end
$var reg 16 Y adres [15:0] $end
$var reg 4 Z iterator [3:0] $end
$upscope $end
$upscope $end
$upscope $end
$enddefinitions $end
#0
$dumpvars
bx Z
bx Y
bx X
bx W
bx V
bx U
bx T
bx S
bx R
bx Q
bx P
b1 O
bx N
bx M
bx L
bx K
bx J
bx I
xH
xG
bx F
xE
bx D
bx C
bx B
bx A
bx @
bx ?
x>
bx =
bx <
bx ;
bx :
bx 9
bx 8
bx 7
bx 6
b1 5
04
03
bx 2
bx 1
bx 0
x/
bx .
bx -
bx ,
bx +
bx *
bx )
bx (
bx '
x&
x%
x$
bx #
bx "
bx !
$end
#1
1$
#2
0$
#3
1$
1&
#4
0$
#5
b0 Y
1>
b0 X
b0 ?
b0 W
b0 C
b0 P
b0 F
0E
b0 B
b0 N
b0 D
b0 Q
b0 A
b0 M
b10001100 U
b10000010 T
b1111000 S
b1101110 R
1$
0&
#6
0$
#7
1$
#8
0$
#9
1$
#10
0$
#11
1$
#12
0$
#13
1$
#14
0$
#15
b0 Z
1$
1&
#16
0$
#17
1$
#18
1E
0$
b1010 .
b1010 =
b11 -
b11 <
b1 ,
b1 ;
b1000 +
b1000 :
b10 *
b10 9
b100 )
b100 8
b11 (
b11 7
b1100 '
b1100 6
0/
0%
#19
1$
#20
0E
0$
1/
#21
1$
#22
0$
b10100 !
b10100 0
b0 #
b0 2
b1 "
b1 1
#23
1$
#24
0H
b1 K
b10100 J
b0 L
0$
1%
#25
b10 C
b10 P
b1 F
1$
#26
0$
#27
b1 Y
b1 A
b1 M
b10 F
b10 X
1$
#28
0$
#29
b0 X
b10100 ?
b10100 W
b0 C
b0 P
b1000 F
1H
1E
1$
0/
0%
#30
0$
#31
b0 Y
b0 A
b0 M
b0 F
b0 ?
b0 W
1$
#32
0$
#33
1$
#34
0$
#35
1$
#36
0$
#37
1$
#38
0$
#39
1$
#40
0$
#41
1$
#42
0$
#43
1$
#44
0$
#45
1$
#46
0$
#47
1$
#48
0$
#49
1$
#50
0$
#51
1$
#52
0$
#53
1$
#54
0$
#55
1$
#56
0$
#57
1$
#58
0$
#59
1$
b100010 .
b100010 =
b101101 -
b101101 <
b111000 ,
b111000 ;
b1000011 +
b1000011 :
b1001110 *
b1001110 9
b1011001 )
b1011001 8
b1001 (
b1001 7
b1111 '
b1111 6
#60
0$
#61
0E
1$
1/
#62
0$
#63
1$
b1010 !
b1010 0
b1 #
b1 2
#64
0G
b1 B
b1 N
0H
b1010 J
b1 L
0$
1%
#65
b0 I
b1110 F
1$
#66
0$
0%
#67
b1 Y
b1 A
b1 M
b1100 F
b10 C
b10 P
1$
#68
0$
#69
b1100 X
b11 C
b11 P
b10 Y
b10100 ?
b10100 W
b1 I
b0 @
b10 A
b10 M
1$
#70
0$
#71
b11 Y
b10 I
b11110 @
b11 A
b11 M
b1 Z
b11110 ?
b11110 W
1$
#72
0$
#73
b100 Y
b10 Z
b101000 ?
b101000 W
b11 I
b100 A
b100 M
1$
#74
0$
#75
b0 Y
b0 A
b0 M
b1010 F
b0 X
b110010 @
b11 Z
b110010 ?
b110010 W
1$
#76
0$
#77
b1100 X
b0 I
b0 C
b0 P
b0 F
b0 ?
b0 W
1H
1$
#78
0$
#79
b0 X
b100 Z
1$
#80
0$
#81
b0 Z
1$
#82
0$
#83
1$
#84
0$
#85
1$
#86
0$
#87
1$
#88
0$
#89
1$
#90
0$
#91
1$
#92
0$
#93
1$
#94
0$
#95
1$
#96
0$
#97
1$
#98
1E
0$
0/
#99
1$
#100
0$
b1010 "
b1010 1
#101
1$
#102
0H
b1010 K
0$
1%
#103
b1110 F
1$
#104
0$
#105
b1010 Y
b1010 A
b1010 M
b11 F
b10 C
b10 P
1$
#106
0$
#107
b1111 D
b1111 Q
b11 C
b11 P
b11 X
b1011 Y
b1 I
b1011 A
b1011 M
1$
#108
0$
#109
b1111 S
b1001 D
b1001 Q
b1100 Y
b10 I
b1100 A
b1100 M
1$
#110
0$
#111
b1011001 D
b1011001 Q
b1001 T
b1101 Y
b11 I
b1101 A
b1101 M
1$
#112
0$
#113
b0 Y
b1011001 U
b0 A
b0 M
b1001110 D
b1001110 Q
b1010 F
1$
#114
0$
#115
b0 D
b0 Q
b0 I
b0 C
b0 P
b0 F
1H
b0 @
1$
#116
0$
#117
b0 X
1$
